Metadata-Version: 2.1
Name: hangman-marking-mock
Version: 0.0.1
Summary: An automated marking system for the hangman project (test)
Home-page: UNKNOWN
Author: Ivan Ying
Author-email: ivan@theaicore.com
License: UNKNOWN
Platform: UNKNOWN
Requires-Python: >=3.6
